cliente_dato_publico/__init__.py
cliente_dato_publico/api_config.py
cliente_dato_publico/main.py
cliente_dato_publico/utils/__init__.py
cliente_dato_publico/utils/exportador.py
cliente_dato_publico-0.1.0.dist-info/METADATA
cliente_dato_publico-0.1.0.dist-info/WHEEL
cliente_dato_publico-0.1.0.dist-info/entry_points.txt
cliente_dato_publico-0.1.0.dist-info/top_level.txt
cliente_dato_publico-0.1.0.dist-info/RECORD
